tgnize/__init__.py
tgnize/app.py
tgnize/util.py
tgnize/model/activity.py
tgnize/model/chat.py
tgnize/model/event.py
tgnize/model/message.py
tgnize/model/plotDataRange.py
tgnize/model/user.py
tgnize/plotting_scripts/activeParticipantsOverTime.py
tgnize/plotting_scripts/minuteBasedAccumulatedTraffic.py
tgnize-0.1.3.dist-info/entry_points.txt
tgnize-0.1.3.dist-info/LICENSE
tgnize-0.1.3.dist-info/WHEEL
tgnize-0.1.3.dist-info/METADATA
tgnize-0.1.3.dist-info/RECORD
