Metadata-Version: 2.1
Name: tgnize
Version: 0.1.3
Summary: How about another exported Telegram Chat analyzer? 😉
Home-page: https://itzmeanjan.github.io/tgnize/
License: UNKNOWN
Author: Anjan Roy
Author-email: anjanroy@yandex.com
Requires-Python: >=3.7
Classifier: Intended Audience :: End Users/Desktop
Classifier: License :: OSI Approved :: MIT License
Classifier: Programming Language :: Python :: 3
Requires-Dist: matplotlib
Requires-Dist: typing
Requires-Dist: beautifulsoup4
Requires-Dist: lxml
Requires-Dist: flit ; extra == "dev"
Provides-Extra: dev
